sanic_swagger/__init__.py
sanic_swagger/doc.py
sanic_swagger/openapi.py
sanic_swagger/options.py
sanic_swagger/serializer.py
sanic_swagger/swagger.py
sanic_swagger/validators.py
sanic_swagger/ui/favicon-16x16.png
sanic_swagger/ui/favicon-32x32.png
sanic_swagger/ui/index.html
sanic_swagger/ui/oauth2-redirect.html
sanic_swagger-0.0.4.dist-info/LICENSE
sanic_swagger-0.0.4.dist-info/METADATA
sanic_swagger-0.0.4.dist-info/WHEEL
sanic_swagger-0.0.4.dist-info/top_level.txt
sanic_swagger-0.0.4.dist-info/RECORD
