Metadata-Version: 2.1
Name: sanic-swagger
Version: 0.0.4
Summary: OpenAPI / Swagger support for Sanic using attrs
Home-page: http://github.com/abatilo/sanic-swagger/
Author: Aaron Batilo
Author-email: aaronbatilo@gmail.com
Maintainer: Aaron Batilo
Maintainer-email: aaronbatilo@gmail.com
License: MIT
Keywords: sanic swagger openapi attrs cattrs
Platform: any
Classifier: Intended Audience :: Developers
Classifier: Development Status :: 4 - Beta
Classifier: Topic :: Software Development :: Libraries :: Python Modules
Classifier: Environment :: Web Environment
Classifier: License :: OSI Approved :: MIT License
Classifier: Programming Language :: Python :: 3.6
Requires-Python: ==3.6.*
Requires-Dist: sanic (>=0.7.0)
Requires-Dist: attrs (>=18.0.0)
